{
  "type": "minecraft:entity",
  "pools": [
    {
      "rolls": 1,
      "entries": [
        {
          "type": "minecraft:item",
          "name": "jurassicadventure:frog_meat",
          "functions": [
            {
              "function": "minecraft:set_count",
              "count": {
                "type": "minecraft:uniform",
                "min": 0,
                "max": 1
              }
            },
            {
              "function": "minecraft:looting_enchant",
              "count": {
                "type": "minecraft:uniform",
                "min": 0,
                "max": 2
              }
            }
          ]
        }
      ]
    },
    {
      "rolls": 1,
      "entries": [
        {
          "type": "minecraft:item",
          "name": "minecraft:slime_ball"
        }
      ],
      "conditions": [
        {
          "condition": "minecraft:random_chance_with_looting",
          "chance": 0.05,
          "looting_multiplier": 0.01
        }
      ]
    }
  ]
}